meeting_availability/__init__.py
meeting_availability/meeting_availability.py
meeting_availability-1.0.4.dist-info/LICENSE
meeting_availability-1.0.4.dist-info/METADATA
meeting_availability-1.0.4.dist-info/WHEEL
meeting_availability-1.0.4.dist-info/top_level.txt
meeting_availability-1.0.4.dist-info/RECORD
