Metadata-Version: 2.1
Name: meeting-availability
Version: 1.0.4
Summary: A module that allows you to know available time blocks for two people to meet.
Home-page: https://github.com/adriwicked/meeting-availability
Author: Adrián Moreno
Author-email: adrianmn90@gmail.com
License: MIT License
Platform: UNKNOWN
Classifier: Programming Language :: Python :: 3
Classifier: License :: OSI Approved :: MIT License
Classifier: Operating System :: OS Independent
License-File: LICENSE
